[{"name": "max", "last_name": "yak", "date_of_birth": "1992-01-03", "chess_id": "19191"}, {"name": "maksym", "last_name": "yakymyshyn", "date_of_birth": "1992-01-03", "chess_id": "19191"}, {"name": "john", "last_name": "doe", "date_of_birth": "1956-11-20", "chess_id": "11122"}, {"name": "dupont", "last_name": "jean", "date_of_birth": "1999-01-01", "chess_id": "12345"}, {"name": "leclerc", "last_name": "centre", "date_of_birth": "1995-05-05", "chess_id": "34344"}, {"name": "Machine", "last_name": "Machine", "date_of_birth": "1111-11-11", "chess_id": "11111"}, {"name": "doublon", "last_name": "doublon", "date_of_birth": "2222-12-12", "chess_id": "22222"}]